rustylib/Rcolor.py
rustylib/Rkon.py
rustylib/Rmath.py
rustylib/Rrandom.py
rustylib/Rrequests.py
rustylib/Rsugaku.py
rustylib/Rusty.py
rustylib/__init__.py
rustylib-1.8.9.dist-info/METADATA
rustylib-1.8.9.dist-info/WHEEL
rustylib-1.8.9.dist-info/top_level.txt
rustylib-1.8.9.dist-info/RECORD
