Metadata-Version: 2.1
Name: rustylib
Version: 1.8.9
Summary: A useful python library for everything.
Home-page: https://github.com/ZeyaTsu/rustylib
Author: ZeyaTsu
Project-URL: Bug Tracker, https://github.com/ZeyaTsu/rustylib/issues
Classifier: Programming Language :: Python :: 3
Classifier: License :: OSI Approved :: MIT License
Classifier: Operating System :: OS Independent
Requires-Python: >=3.6
